decube_auth/__init__.py
decube_auth/client.py
decube_auth/config.py
decube_auth/exceptions.py
decube_auth-0.1.0.dist-info/METADATA
decube_auth-0.1.0.dist-info/WHEEL
decube_auth-0.1.0.dist-info/top_level.txt
decube_auth-0.1.0.dist-info/RECORD
