Metadata-Version: 2.4
Name: decube-auth
Version: 0.1.0
Summary: Decube Auth SDK for signup, login, and token refresh
Author-email: Decube Innovation Labs <enquiry@decubelabs.com>
License: MIT
Project-URL: Homepage, https://github.com/DecubeInnovationLabs
Project-URL: Repository, https://github.com/DecubeInnovationLabs/decube-auth-sdk
Requires-Python: >=3.9
Requires-Dist: requests>=2.28
